file_state_manager/__init__.py
file_state_manager/cloneable_file.py
file_state_manager/file_state_manager_base.py
file_state_manager/util_object_hash.py
file_state_manager-3.0.1.dist-info/licenses/LICENSE
file_state_manager-3.0.1.dist-info/METADATA
file_state_manager-3.0.1.dist-info/WHEEL
file_state_manager-3.0.1.dist-info/top_level.txt
file_state_manager-3.0.1.dist-info/RECORD
