Metadata-Version: 2.4
Name: file_state_manager
Version: 3.0.1
Summary: This package allows you to easily undo and redo saved data in your applications.
Author: Masahide Mori
License-Expression: MIT
Project-URL: Homepage, https://github.com/MasahideMori-SimpleAppli/file_state_manager_py
Classifier: Programming Language :: Python :: 3
Classifier: Programming Language :: Python :: 3.10
Classifier: Programming Language :: Python :: 3.11
Classifier: Programming Language :: Python :: 3.12
Classifier: Programming Language :: Python :: 3.13
Classifier: Operating System :: OS Independent
Requires-Python: >=3.10
License-File: LICENSE
Dynamic: license-file
